[
  {"q": "Cine a fost membru fondator al trupei The Beatles?",
    "c": "John Lennon", 
    "w1": "Mick Jagger",
    "w2": "David Bowie", 
    "w3": "Elton John"},
  {"q": "Cine a fost solistul principal al trupei The Beatles?", 
    "c": "John Lennon", 
    "w1": "Ringo Starr", 
    "w2": "Paul McCartney", 
    "w3": "George Harrison"},
  {"q": "În ce oraș a fost formată trupa The Beatles?", 
    "c": "Liverpool", 
    "w1": "Londra",
    "w2": "Manchester", 
    "w3": "Birmingham"}, 
  {"q": "Care este anul lansării albumului \"Sgt. Pepper's Lonely Hearts Club Band\"?", 
    "c": "1967", 
    "w1": "1965", 
    "w2": "1969", 
    "w3": "1971"},
  {"q": "Cine a compus majoritatea pieselor trupei The Beatles?", 
    "c": "Paul McCartney", 
    "w1": "John Lennon", 
    "w2": "George Harrison", 
    "w3": "Ringo Starr"},
  {"q": "Care este cel mai bine vândut album al trupei The Beatles?", 
    "c": "\"The White Album\"", 
    "w1": "\"Let It Be\"", 
    "w2": "\"Revolver\"", 
    "w3": "\"Abbey Road\""}, 
  {"q": "Care membru al trupei The Beatles a scris piesa \"Here Comes the Sun\"?", 
    "c": "George Harrison", 
    "w1": "Ringo Starr", 
    "w2": "Paul McCartney", 
    "w3": "John Lennon"}, 
  {"q": "Care este titlul piesei care începe cu versurile \"Yesterday, all my troubles seemed so far away\"?", 
    "w1": "\"Let It Be\"", 
    "c": "\"Yesterday\"", 
    "w2": "\"Help!\"", 
    "w3": "\"Hey Jude\""},
  {"q": "Cine a fost managerul trupei The Beatles?", 
    "c": "Brian Epstein", 
    "w1": "Andrew Loog Oldham", 
    "w2": "Allen Klein", 
    "w3": "George Martin"}, 
  {"q": "Care este albumul de debut al trupei The Beatles?",
    "c": "\"Please Please Me\"", 
    "w1": "\"Help!\"", 
    "w2": "\"Rubber Soul\"", 
    "w3": "\"A Hard Day's Night\""}, 
  {"q": "Care membru al trupei The Beatles a compus piesa \"While My Guitar Gently Weeps\"?", 
    "c": "George Harrison", 
    "w1": "Ringo Starr", 
    "w2": "Paul McCartney", 
    "w3": "John Lennon"}, 
  {"q": "Cine a fost producătorul muzical principal al trupei The Beatles?", 
    "c": "George Martin", 
    "w1": "Phil Spector", 
    "w2": "Brian Wilson", 
    "w3": "Quincy"}, 
  {"q": "Care este albumul considerat a fi unul dintre cele mai inovatoare și influente din istoria muzicii rock?", 
    "c": "\"Sgt. Pepper's Lonely Hearts Club Band\"", 
    "w1": "\"Abbey Road\"", 
    "w2": "\"Rubber Soul\"", 
    "w3": "\"Revolver\""},
  {"q": "Care a fost primul film al trupei The Beatles?", 
    "c": "\"A Hard Day's Night\"", 
    "w1": "\"Help!\"", 
    "w2": "\"Yellow Submarine\"", 
    "w3": "\"Let It Be\""},
  {"q": "Care este cel mai vândut single al trupei The Beatles?", 
    "c": "\"I Want to Hold Your Hand\"", 
    "w1": "\"Yesterday\"", 
    "w2": "\"Let It Be\"", 
    "w3": "\"Hey Jude\""}, 
  {"q": "Cine a fost membru al trupei The Beatles, dar a părăsit formația înainte de succesul lor?", 
    "c": "Pete Best", 
    "w1": "Stuart Sutcliffe", 
    "w2": "Billy Preston", 
    "w3": "Eric Clapton"}, 
  {"q": "Care a fost ultimul album lansat de The Beatles înainte de destrămarea oficială a trupei?", 
    "c": "\"Let It Be\"", 
    "w1": "\"Abbey Road\"", 
    "w2": "\"The White Album\"", 
    "w3": "\"Revolver\""}, 
  {"q": "Care este cel mai lung cântec al trupei The Beatles?", 
    "c": "\"A Day in the Life\"", 
    "w1": "\"Hey Jude\"", 
    "w2": "\"Let It Be\"", 
    "w3": "\"Yesterday\""}
]